bert_g2p/__init__.py
bert_g2p/bert_g2p.py
bert_g2p-0.0.9.dist-info/LICENSE
bert_g2p-0.0.9.dist-info/METADATA
bert_g2p-0.0.9.dist-info/WHEEL
bert_g2p-0.0.9.dist-info/top_level.txt
bert_g2p-0.0.9.dist-info/RECORD
