Metadata-Version: 2.2
Name: bert-g2p
Version: 0.0.9
Summary: BERT with G2P
Home-page: https://github.com/pengzhendong/bert-g2p
Author: Zhendong Peng
Author-email: pzd17@tsinghua.org.cn
Classifier: Programming Language :: Python :: 3
Classifier: Operating System :: OS Independent
Classifier: Topic :: Scientific/Engineering
License-File: LICENSE
Requires-Dist: g2p-mix
Requires-Dist: modelscope
Requires-Dist: torch
Requires-Dist: transformers
Dynamic: author
Dynamic: author-email
Dynamic: classifier
Dynamic: description
Dynamic: description-content-type
Dynamic: home-page
Dynamic: requires-dist
Dynamic: summary
